MANIFEST.in
setup.py
RedirectsPlugin.egg-info/PKG-INFO
RedirectsPlugin.egg-info/SOURCES.txt
RedirectsPlugin.egg-info/dependency_links.txt
RedirectsPlugin.egg-info/entry_points.txt
RedirectsPlugin.egg-info/not-zip-safe
RedirectsPlugin.egg-info/top_level.txt
redirects/__init__.py
redirects/api.py
redirects/db_default.py
redirects/templates/admin_redirects.html