Metadata-Version: 1.0
Name: RedirectsPlugin
Version: 0.1.2
Summary: Define server-side redirects in Trac.
Home-page: http://mitar.tnode.com/
Author: Mitar
Author-email: mitar.trac@tnode.com
License: AGPLv3
Keywords: trac plugin
Platform: UNKNOWN
